<?xml version="1.0" encoding="UTF-8"?>
<odoo>
    <data>

        <record id="pos_config_view_form_inherit" model="ir.ui.view">
            <field name="name">pos.config.form.view.inherit</field>
            <field name="model">pos.config</field>
            <field name="inherit_id" ref="point_of_sale.pos_config_view_form"/>
            <field name="arch" type="xml">
                <xpath expr="//div[@id='company']" position="after">
                    <h2>Branch</h2>
                    <div class="row mt16 o_settings_container" id="pos_branch">
                        <div class="col-12 col-lg-6 o_setting_box" id="branch">
                            <div class="o_setting_right_pane">
                                <span class="o_form_label">Branch</span>
                                <div class="text-muted">
                                    Branch related
                                </div>
                                <div class="content-group mt16">
                                    <field name="pos_branch_id" colspan="4" nolabel="1"/>
                                </div>
                            </div>
                        </div>
                    </div>
                    <h2>Delivery</h2>
                    <div class="row mt16 o_settings_container" id="pos_branch">
                        <div class="col-12 col-lg-6 o_setting_box" id="branch">
                            <div class="o_setting_right_pane">
                                <span class="o_form_label">Delivery</span>
                                <div class="text-muted">
                                    Delivery Product
                                </div>
                                <div class="content-group mt16">
                                    <field name="delivery_product_id" colspan="4" nolabel="1"/>
                                </div>
                            </div>
                        </div>
                    </div>
                    <h2>Default Customer</h2>
                    <div class="row mt16 o_settings_container" id="pos_branch">
                        <div class="col-12 col-lg-6 o_setting_box" id="branch">
                            <div class="o_setting_right_pane">
                                <span class="o_form_label">Customer</span>
                                <div class="text-muted">
                                    Default Customer
                                </div>
                                <div class="content-group mt16">
                                    <field name="default_partner_id" domain="[('customer', '=', True)]" colspan="4" nolabel="1"/>
                                </div>
                            </div>
                        </div>
                    </div>
                </xpath>
            </field>
        </record>


        <record id="view_pos_config_kanban_inherit" model="ir.ui.view">
            <field name="name">pos.config.kanban.view.inherit</field>
            <field name="model">pos.config</field>
            <field name="inherit_id" ref="point_of_sale.view_pos_config_kanban"/>
            <field name="arch" type="xml">
                <xpath expr="//button[@name='open_session_cb']" position="after">
                    <button t-if="!record.current_session_id.raw_value &amp;&amp; !record.pos_session_username.value" class="btn btn-primary" name="%(bi_foodics_integration.action_import_foodics_wizard)d" type="action">Import Foodics Data</button>
                </xpath>
            </field>
        </record>

        <record id="view_pos_session_form_inherit" model="ir.ui.view">
            <field name="name">pos.session.form.view.inherit</field>
            <field name="model">pos.session</field>
            <field name="inherit_id" ref="point_of_sale.view_pos_session_form"/>
            <field name="arch" type="xml">
                <xpath expr="//field[@name='start_at']" position="before">
                    <field name="st_date"/>
                </xpath>
                <xpath expr="//button[@name='action_pos_session_validate']" position="after">
                    <button class="btn btn-primary" context="{'default_pos_id': config_id}" name="%(bi_foodics_integration.action_import_foodics_per_session_wizard)d" type="action" string="Import Foodics Data" attrs="{'invisible': [('state', 'not in', ['opened'])]}"/>
                </xpath>
            </field>
        </record>

    </data>
</odoo>